LICENSE
MANIFEST.in
README.md
setup.py
libpythonpro_mlpdf/__init__.py
libpythonpro_mlpdf/github_api.py
libpythonpro_mlpdf.egg-info/PKG-INFO
libpythonpro_mlpdf.egg-info/SOURCES.txt
libpythonpro_mlpdf.egg-info/dependency_links.txt
libpythonpro_mlpdf.egg-info/not-zip-safe
libpythonpro_mlpdf.egg-info/requires.txt
libpythonpro_mlpdf.egg-info/top_level.txt
libpythonpro_mlpdf/spam/__init__.py
libpythonpro_mlpdf/spam/db.py
libpythonpro_mlpdf/spam/enviador_de_email.py
libpythonpro_mlpdf/spam/main.py
libpythonpro_mlpdf/spam/modelos.py
libpythonpro_mlpdf/tests/__init__.py
libpythonpro_mlpdf/tests/test_exemplo.py
libpythonpro_mlpdf/tests/test_spam/__init__.py
libpythonpro_mlpdf/tests/test_spam/conftest.py
libpythonpro_mlpdf/tests/test_spam/test_enviador_de_email.py
libpythonpro_mlpdf/tests/test_spam/test_envio_para_base_de_usuarios.py
libpythonpro_mlpdf/tests/test_spam/test_github_api.py
libpythonpro_mlpdf/tests/test_spam/test_usuarios.py