Metadata-Version: 2.1
Name: libpythonpro_mlpdf
Version: 0.3
Summary: Módulo para exemplificar construção de projetos Python no curso PyTools
Home-page: https://github.com/matheuspdf/libpythonpro
Author: Matheus Lopes
Author-email: matheuslopes.pdf@gmail.com
License:                     GNU AFFERO GENERAL PUBLIC LICENSE
Classifier: Development Status :: 2 - Pre-Alpha
Classifier: Environment :: Console
Classifier: Intended Audience :: Developers
Classifier: License :: OSI Approved :: GNU Affero General Public License v3 or later (AGPLv3+)
Classifier: Operating System :: OS Independent
Classifier: Programming Language :: Python :: 3.10
Classifier: Framework :: Pytest
License-File: LICENSE
Requires-Dist: requests
